{
  "animateLoading": true,
  "borderRadius": "{{appsmith.theme.borderRadius.appBorderRadius}}",
  "bottomRow": 4,
  "boxShadow": "none",
  "buttonColor": "#86efac",
  "buttonStyle": "PRIMARY_BUTTON",
  "buttonVariant": "PRIMARY",
  "disabledWhenInvalid": false,
  "dynamicBindingPathList": [
    {
      "key": "borderRadius"
    }
  ],
  "dynamicTriggerPathList": [
    {
      "key": "onClick"
    }
  ],
  "iconAlign": "left",
  "iconName": "send-to",
  "isDefaultClickDisabled": true,
  "isDisabled": false,
  "isLoading": false,
  "isVisible": true,
  "key": "ax40hi8118",
  "leftColumn": 41,
  "minWidth": 120,
  "mobileBottomRow": 22,
  "mobileLeftColumn": 47,
  "mobileRightColumn": 63,
  "mobileTopRow": 18,
  "needsErrorInfo": false,
  "onClick": "{{Welcome.run()}}",
  "originalBottomRow": 22,
  "originalTopRow": 18,
  "parentId": "q6okq918zd",
  "placement": "CENTER",
  "recaptchaType": "V3",
  "renderMode": "CANVAS",
  "resetFormOnClick": false,
  "responsiveBehavior": "hug",
  "rightColumn": 57,
  "text": "Send Email",
  "topRow": 0,
  "type": "BUTTON_WIDGET",
  "version": 1,
  "widgetId": "e2zi1ndp9e",
  "widgetName": "wlcm_Send"
}