{
  "gitSyncId": "6668cf0988cf8166d347b04c_6b3a0be6-5656-4fa0-803b-b614b161b97b",
  "id": "Shopping_jsEntity.entityDelete",
  "pluginId": "js-plugin",
  "pluginType": "JS",
  "unpublishedAction": {
    "actionConfiguration": {
      "encodeParamsToggle": true,
      "jsArguments": [],
      "paginationType": "NONE",
      "timeoutInMillisecond": 10000
    },
    "collectionId": "Shopping_jsEntity",
    "confirmBeforeExecute": false,
    "datasource": {
      "isAutoGenerated": false,
      "name": "UNUSED_DATASOURCE",
      "pluginId": "js-plugin"
    },
    "dynamicBindingPathList": [
      {
        "key": "body"
      }
    ],
    "fullyQualifiedName": "jsEntity.entityDelete",
    "name": "entityDelete",
    "pageId": "Shopping",
    "runBehaviour": "MANUAL",
    "userSetOnLoad": false
  }
}