{
  "gitSyncId": "6668cf0988cf8166d347b04c_d8f11083-d95c-4ae0-8bd0-3c822dd52a44",
  "id": "Product_n8nVals.clearVals",
  "pluginId": "js-plugin",
  "pluginType": "JS",
  "unpublishedAction": {
    "actionConfiguration": {
      "encodeParamsToggle": true,
      "jsArguments": [],
      "paginationType": "NONE",
      "timeoutInMillisecond": 10000
    },
    "collectionId": "Product_n8nVals",
    "confirmBeforeExecute": false,
    "datasource": {
      "isAutoGenerated": false,
      "name": "UNUSED_DATASOURCE",
      "pluginId": "js-plugin"
    },
    "dynamicBindingPathList": [
      {
        "key": "body"
      }
    ],
    "fullyQualifiedName": "n8nVals.clearVals",
    "name": "clearVals",
    "pageId": "Product",
    "runBehaviour": "MANUAL",
    "userSetOnLoad": false
  }
}