{
  "gitSyncId": "6668cf0988cf8166d347b04c_61bf3e7f-2e1c-490e-9fbf-158d476c7836",
  "id": "Product Type_task_List",
  "pluginId": "mysql-plugin",
  "pluginType": "DB",
  "unpublishedAction": {
    "actionConfiguration": {
      "body": "select ordr Ord, name Task, ifnull(description,'') Description\nfrom  tasks a\nwhere  a.product_type_id = {{appsmith.store.prodTypeID}}\nand active = 1\norder by ordr, name;",
      "encodeParamsToggle": true,
      "paginationType": "NONE",
      "pluginSpecifiedTemplates": [
        {
          "value": true
        }
      ],
      "timeoutInMillisecond": 10000
    },
    "confirmBeforeExecute": false,
    "datasource": {
      "id": "wf_api",
      "isAutoGenerated": false,
      "name": "wf_api",
      "pluginId": "mysql-plugin"
    },
    "dynamicBindingPathList": [
      {
        "key": "body"
      }
    ],
    "name": "task_List",
    "pageId": "Product Type",
    "runBehaviour": "ON_PAGE_LOAD",
    "userSetOnLoad": false
  }
}