{
  "gitSyncId": "6668cf0988cf8166d347b04c_c465c8d6-3b40-4435-b9b1-d64ccdc8a9db",
  "id": "Product Type Task_jsEntity.editModeRun",
  "pluginId": "js-plugin",
  "pluginType": "JS",
  "unpublishedAction": {
    "actionConfiguration": {
      "encodeParamsToggle": true,
      "jsArguments": [],
      "paginationType": "NONE",
      "timeoutInMillisecond": 10000
    },
    "collectionId": "Product Type Task_jsEntity",
    "confirmBeforeExecute": false,
    "datasource": {
      "isAutoGenerated": false,
      "name": "UNUSED_DATASOURCE",
      "pluginId": "js-plugin"
    },
    "dynamicBindingPathList": [
      {
        "key": "body"
      }
    ],
    "executeOnLoad": false,
    "fullyQualifiedName": "jsEntity.editModeRun",
    "name": "editModeRun",
    "pageId": "Product Type Task",
    "userSetOnLoad": false
  }
}