{
  "gitSyncId": "6668cf0988cf8166d347b04c_264de7a3-2fb2-41a0-b14d-410fd056c9b9",
  "id": "n8n-Connect_dd_ingredient_batch",
  "pluginId": "restapi-plugin",
  "pluginType": "API",
  "unpublishedAction": {
    "actionConfiguration": {
      "autoGeneratedHeaders": [
        {
          "key": "content-type",
          "value": "application/json"
        }
      ],
      "body": "{\n    \"function\": \"whatsfresh.dd_ingredient_batches\",\n    \"params\": { \"userEmail\": \"{{appsmith.user.email}}\" },\n    \"source\": {{appsmith.appName}},\n\t  \"format\": \"json\",\n    \"type\": \"json\"\n}",
      "bodyFormData": [],
      "encodeParamsToggle": true,
      "formData": {
        "apiContentType": "application/json"
      },
      "headers": [],
      "httpMethod": "POST",
      "httpVersion": "HTTP11",
      "paginationType": "NONE",
      "path": "",
      "pluginSpecifiedTemplates": [
        {
          "value": true
        }
      ],
      "queryParameters": [],
      "timeoutInMillisecond": 10000
    },
    "confirmBeforeExecute": false,
    "datasource": {
      "id": "n8n-hydrate",
      "isAutoGenerated": false,
      "name": "n8n-hydrate",
      "pluginId": "restapi-plugin"
    },
    "dynamicBindingPathList": [
      {
        "key": "body"
      }
    ],
    "name": "dd_ingredient_batch",
    "pageId": "n8n-Connect",
    "runBehaviour": "AUTOMATIC",
    "userSetOnLoad": false
  }
}